gus_nba_tools/NBASeasonDataCollector.py
gus_nba_tools/__init__.py
gus_nba_tools/player_data_processor.py
gus_nba_tools/player_opp_pts_allowed_merge.py
gus_nba_tools/team_data_processor.py
gus_nba_tools-0.2.3.dist-info/METADATA
gus_nba_tools-0.2.3.dist-info/WHEEL
gus_nba_tools-0.2.3.dist-info/top_level.txt
gus_nba_tools-0.2.3.dist-info/RECORD
